xtream/__init__.py
xtream/main.py
xtream/nstream/__init__.py
xtream/nstream/os/__init__.py
xtream/nstream/os/base.py
xtream/nstream/os/centos/__init__.py
xtream/nstream/os/centos/main.py
xtream/nstream/os/ubuntu/__init__.py
xtream/nstream/os/ubuntu/main.py
xtream/nstream/os/windows/__init__.py
xtream/nstream/os/windows/main.py
xtream/nstream/packages/__init__.py
xtream-0.6.5.dist-info/LICENSE.txt
xtream-0.6.5.dist-info/METADATA
xtream-0.6.5.dist-info/WHEEL
xtream-0.6.5.dist-info/entry_points.txt
xtream-0.6.5.dist-info/namespace_packages.txt
xtream-0.6.5.dist-info/top_level.txt
xtream-0.6.5.dist-info/RECORD
